LICENSE.txt
README.md
setup.py
anna/__init__.py
anna/actions.py
anna/asserts.py
anna/report.py
anna_api_test_framework.egg-info/PKG-INFO
anna_api_test_framework.egg-info/SOURCES.txt
anna_api_test_framework.egg-info/dependency_links.txt
anna_api_test_framework.egg-info/requires.txt
anna_api_test_framework.egg-info/top_level.txt